<?xml version="1.0" encoding="UTF-8"?>
<con:operation action="http://www.soapui.org/sample/login" name="login" bindingOperationName="login" inputName="" isOneWay="false" receivesAttachments="false" sendsAttachments="false" type="Request-Response" id="ab916bf8-dd24-4ce4-9be4-3947dc28025e" xmlns:xsi="http://www.w3.org/2001/XMLSchema-instance" xmlns:con="http://eviware.com/soapui/config">
  <con:settings>
    <con:setting id="728cfde6-25de-45ec-805a-c4905d874219fileName">login</con:setting>
    <con:setting id="ab916bf8-dd24-4ce4-9be4-3947dc28025efileName">login</con:setting>
  </con:settings>
  <con:call name="login rq" outgoingWss="" incomingWss="" id="c453a6e9-280b-4442-957f-3efa8ed61fa4" defaultOutgoingWss="" defaultIncomingWss="">
    <con:settings>
      <con:setting id="com.eviware.soapui.impl.wsdl.WsdlRequest@request-headers">&lt;xml-fragment/></con:setting>
    </con:settings>
    <con:encoding>UTF-8</con:encoding>
    <con:endpoint>http://127.0.0.1:8083/mockServiceSoapBinding</con:endpoint>
    <con:request><![CDATA[<soapenv:Envelope xmlns:soapenv="http://schemas.xmlsoap.org/soap/envelope/" xmlns:sam="http://www.soapui.org/sample/">
 <soapenv:Header/>
 <soapenv:Body>
 <sam:login>
 <username>Login</username>
 <password>Login123</password>
 </sam:login>
 </soapenv:Body>
</soapenv:Envelope>]]></con:request>
    <con:credentials>
      <con:username xsi:nil="true"/>
      <con:password xsi:nil="true"/>
      <con:domain xsi:nil="true"/>
      <con:selectedAuthProfile>No Authorization</con:selectedAuthProfile>
      <con:authType>No Authorization</con:authType>
    </con:credentials>
    <con:jmsConfig JMSDeliveryMode="PERSISTENT"/>
    <con:jmsPropertyConfig/>
    <con:wsaConfig mustUnderstand="NONE" version="200508"/>
    <con:wsrmConfig version="1.2"/>
    <con:environmentSpec>
      <con:entry environmentId="f27a7295-1f08-4642-a3be-7ae9878517f0">
        <con:authProfile>No Authorization</con:authProfile>
      </con:entry>
      <con:entry environmentId="712e7e53-7afa-4695-8bf2-bc7b9af8c08a">
        <con:authProfile>No Authorization</con:authProfile>
      </con:entry>
      <con:entry environmentId="834e9f34-445a-4d32-b042-ef79046664e3">
        <con:authProfile>Inherit From Parent</con:authProfile>
      </con:entry>
      <con:entry environmentId="19b3aa32-a1f5-474e-bd47-6ecf34074e03">
        <con:authProfile>Inherit From Parent</con:authProfile>
      </con:entry>
      <con:entry environmentId="8adf9beb-0001-459f-b854-d8161046b013">
        <con:authProfile>Inherit From Parent</con:authProfile>
      </con:entry>
      <con:entry environmentId="85fcf76d-cc70-4a0b-a2f6-7b043cf8233a">
        <con:authProfile>Inherit From Parent</con:authProfile>
      </con:entry>
      <con:entry environmentId="aaa8e0b8-c982-402f-aabc-53999ad72736">
        <con:authProfile>Inherit From Parent</con:authProfile>
      </con:entry>
      <con:entry environmentId="613bb63e-dfae-4525-8f53-7cc0745a1be1">
        <con:authProfile>Inherit From Parent</con:authProfile>
      </con:entry>
      <con:entry environmentId="c7173b3a-fee4-45c8-906c-55deaef4eb0d">
        <con:authProfile>Inherit From Parent</con:authProfile>
      </con:entry>
    </con:environmentSpec>
  </con:call>
  <con:environmentSpec>
    <con:entry environmentId="834e9f34-445a-4d32-b042-ef79046664e3">
      <con:authProfile>Inherit From Parent</con:authProfile>
    </con:entry>
    <con:entry environmentId="19b3aa32-a1f5-474e-bd47-6ecf34074e03">
      <con:authProfile>Inherit From Parent</con:authProfile>
    </con:entry>
    <con:entry environmentId="8adf9beb-0001-459f-b854-d8161046b013">
      <con:authProfile>Inherit From Parent</con:authProfile>
    </con:entry>
    <con:entry environmentId="85fcf76d-cc70-4a0b-a2f6-7b043cf8233a">
      <con:authProfile>Inherit From Parent</con:authProfile>
    </con:entry>
    <con:entry environmentId="aaa8e0b8-c982-402f-aabc-53999ad72736">
      <con:authProfile>Inherit From Parent</con:authProfile>
    </con:entry>
    <con:entry environmentId="613bb63e-dfae-4525-8f53-7cc0745a1be1">
      <con:authProfile>Inherit From Parent</con:authProfile>
    </con:entry>
    <con:entry environmentId="c7173b3a-fee4-45c8-906c-55deaef4eb0d">
      <con:authProfile>Inherit From Parent</con:authProfile>
    </con:entry>
  </con:environmentSpec>
</con:operation>
